{
    "MPN": [
        false,
        "KTR18EZPF1653"
    ],
    "base": "757a90dd-0998-43fc-b546-dfa2ee964885",
    "datasheet": [
        true,
        ""
    ],
    "description": [
        false,
        "HV Chip Resistor 165 kΩ 1% 0.25W 500V"
    ],
    "inherit_model": true,
    "inherit_tags": true,
    "manufacturer": [
        true,
        ""
    ],
    "parametric": {
        "pmax": "0.25",
        "table": "resistors",
        "tolerance": "1",
        "value": "165000.00"
    },
    "tags": [],
    "type": "part",
    "uuid": "3a5c38f4-39b4-4f2c-8593-73a95c4c32c1",
    "value": [
        false,
        "165 kΩ"
    ]
}